Metadata-Version: 1.0
Name: dsnd-probability-testing
Version: 0.2
Summary: Gaussian and binomial distributions
Home-page: UNKNOWN
Author: Yasmin Cortez
Author-email: yasmincrtz@gmail.com
License: UNKNOWN
Platform: UNKNOWN
